config/api_endpoints.yaml
crustdata_mcp/__init__.py
crustdata_mcp/cli.py
src/server.py
src/validators.py
crustdata_screener_mcp-1.0.3.dist-info/METADATA
crustdata_screener_mcp-1.0.3.dist-info/WHEEL
crustdata_screener_mcp-1.0.3.dist-info/entry_points.txt
crustdata_screener_mcp-1.0.3.dist-info/top_level.txt
crustdata_screener_mcp-1.0.3.dist-info/RECORD
