Metadata-Version: 2.4
Name: crustdata-screener-mcp
Version: 1.0.3
Summary: MCP server wrapper for CrustData Screener APIs
Author-email: CrustData <support@crustdata.com>
Requires-Python: >=3.10
Requires-Dist: mcp>=1.0.0
Requires-Dist: httpx>=0.27.0
Requires-Dist: pyyaml>=6.0.0
Requires-Dist: python-dotenv>=1.0.0
